debmans/__main__.py
debmans/extractor.py
debmans/renderer.py
debmans/command.py
debmans/__init__.py
debmans/logger.py
debmans/_version.py
debmans/utils.py
debmans/static/debian.css
debmans/static/template.html
debmans/static/index.mdwn
debmans/static/search.js
debmans/static/404.mdwn
debmans/static/Pics/openlogo-50.png
debmans/static/Pics/admon-tip.png
debmans/static/Pics/admon-warning.png
debmans/static/Pics/admon-important.png
debmans/static/Pics/gradient.png
debmans/static/Pics/emblem-downloads.png
debmans/static/Pics/admon-note.png
debmans/static/Pics/gradient-flipped.png
debmans-1.0.0.dist-info/METADATA
debmans-1.0.0.dist-info/RECORD
debmans-1.0.0.dist-info/DESCRIPTION.rst
debmans-1.0.0.dist-info/entry_points.txt
debmans-1.0.0.dist-info/top_level.txt
debmans-1.0.0.dist-info/WHEEL
debmans-1.0.0.dist-info/metadata.json
