Metadata-Version: 2.0
Name: debmans
Version: 1.0.0
Summary: Extract and render manuals from Debian packages
Home-page: https://debmans.readthedocs.io/
Author: Antoine Beaupré
Author-email: anarcat@debian.org
License: AGPLv3
Platform: Debian
Classifier: Development Status :: 5 - Production/Stable
Classifier: Environment :: Console
Classifier: Environment :: Web Environment
Classifier: Intended Audience :: End Users/Desktop
Classifier: Intended Audience :: Developers
Classifier: Intended Audience :: System Administrators
Classifier: Intended Audience :: Information Technology
Classifier: License :: OSI Approved :: GNU Affero General Public License v3 or later (AGPLv3+)
Classifier: Natural Language :: English
Classifier: Operating System :: POSIX :: Linux
Classifier: Programming Language :: Python
Classifier: Programming Language :: Python :: 2
Classifier: Programming Language :: Python :: 2.7
Classifier: Programming Language :: Python :: 2 :: Only
Classifier: Topic :: Documentation
Classifier: Topic :: Internet :: WWW/HTTP :: Indexing/Search
Classifier: Topic :: Software Development :: Libraries :: Python Modules
Classifier: Topic :: System :: Archiving :: Packaging
Classifier: Topic :: Text Processing :: Markup :: HTML
Requires-Dist: python-apt
Requires-Dist: click
Requires-Dist: python-debian
Requires-Dist: humanize
Requires-Dist: jinja2
Requires-Dist: markdown
Provides-Extra: dev
Requires-Dist: pytest; extra == 'dev'
Requires-Dist: tox; extra == 'dev'
Requires-Dist: pyflakes; extra == 'dev'
